Workbook

Sheet CONSOLIDADO
B2: DATA BASE
B3: 46077
D5: PRODUTOS
B6: Assessor | C6: Equipe | D6: Nome Assessor | E6: Renda Fixa (Primário + Secundário) | F6: Renda Variavel (Corretagem) | G6: Renda Variavel (PE) | H6: Câmbio | I6: Fundos Fechados (Primário + Secundário) | J6: COE | K6: Receita Geral
B7: 69519 | C7: LEBLON | D7: NICOLAS KERSUL | E7: =(SUMIF('SECUNDÁRIO RF'!C:C,CONSOLIDADO!B7,'SECUNDÁRIO RF'!N:N)/2)+(SUMIF('PRIMARIO RF'!B:B,CONSOLIDADO!B7,'PRIMARIO RF'!U:U)) -> 19018.5 | F7: =SUMIF('RENDA VARIAVEL | CORRETAGEM'!D:D,CONSOLIDADO!B7,'RENDA VARIAVEL | CORRETAGEM'!H:H)*0.75 -> 5171.4825 | G7: =SUMIF('RENDA VARIAVEL | ESTRUTURADAS'!I:I,CONSOLIDADO!B7,'RENDA VARIAVEL | ESTRUTURADAS'!G:G) -> 3451.1 | H7: =SUMIF(CÂMBIO!G:G,CONSOLIDADO!B7,CÂMBIO!O:O)/2 -> 161.33335 | I7: =((SUMIF('FUNDOS FECHADOS'!J:J,CONSOLIDADO!B7,'FUNDOS FECHADOS'!I:I))*0.85)+(SUMIF('SECUNDARIO FUNDOS'!D:D,CONSOLIDADO!B7,'SECUNDARIO FUNDOS'!O:O)) -> 0 | J7: =SUMIF(COE!B:B,CONSOLIDADO!B7,COE!K:K) -> 0 | K7: =SUM(E7:J7) -> 27802.416
B8: 27086 | C8: SP | D8: LUCAS GEORGINI | E8: =(SUMIF('SECUNDÁRIO RF'!C:C,CONSOLIDADO!B8,'SECUNDÁRIO RF'!N:N)/2)+(SUMIF('PRIMARIO RF'!B:B,CONSOLIDADO!B8,'PRIMARIO RF'!U:U)) -> 3469 | F8: =SUMIF('RENDA VARIAVEL | CORRETAGEM'!D:D,CONSOLIDADO!B8,'RENDA VARIAVEL | CORRETAGEM'!H:H)*0.75 -> 1421.19 | G8: =SUMIF('RENDA VARIAVEL | ESTRUTURADAS'!I:I,CONSOLIDADO!B8,'RENDA VARIAVEL | ESTRUTURADAS'!G:G) -> 0 | H8: =SUMIF(CÂMBIO!G:G,CONSOLIDADO!B8,CÂMBIO!O:O)/2 -> 794.01 | I8: =((SUMIF('FUNDOS FECHADOS'!J:J,CONSOLIDADO!B8,'FUNDOS FECHADOS'!I:I))*0.85)+(SUMIF('SECUNDARIO FUNDOS'!D:D,CONSOLIDADO!B8,'SECUNDARIO FUNDOS'!O:O)) -> 0 | J8: =SUMIF(COE!B:B,CONSOLIDADO!B8,COE!K:K) -> 0 | K8: =SUM(E8:J8) -> 5684.2
B9: 49894 | C9: SP | D9: VICTOR GODOY | E9: =(SUMIF('SECUNDÁRIO RF'!C:C,CONSOLIDADO!B9,'SECUNDÁRIO RF'!N:N)/2)+(SUMIF('PRIMARIO RF'!B:B,CONSOLIDADO!B9,'PRIMARIO RF'!U:U)) -> 32617 | F9: =SUMIF('RENDA VARIAVEL | CORRETAGEM'!D:D,CONSOLIDADO!B9,'RENDA VARIAVEL | CORRETAGEM'!H:H)*0.75 -> 4720.23 | G9: =SUMIF('RENDA VARIAVEL | ESTRUTURADAS'!I:I,CONSOLIDADO!B9,'RENDA VARIAVEL | ESTRUTURADAS'!G:G) -> 0 | H9: =SUMIF(CÂMBIO!G:G,CONSOLIDADO!B9,CÂMBIO!O:O)/2 -> 701.29095 | I9: =((SUMIF('FUNDOS FECHADOS'!J:J,CONSOLIDADO!B9,'FUNDOS FECHADOS'!I:I))*0.85)+(SUMIF('SECUNDARIO FUNDOS'!D:D,CONSOLIDADO!B9,'SECUNDARIO FUNDOS'!O:O)) -> 33911.731 | J9: =SUMIF(COE!B:B,CONSOLIDADO!B9,COE!K:K) -> 0 | K9: =SUM(E9:J9) -> 71950.252
B10: 96553 | C10: SP | D10: TAMIRES TEODORO | E10: =(SUMIF('SECUNDÁRIO RF'!C:C,CONSOLIDADO!B10,'SECUNDÁRIO RF'!N:N)/2)+(SUMIF('PRIMARIO RF'!B:B,CONSOLIDADO!B10,'PRIMARIO RF'!U:U)) -> 1145.5 | F10: =SUMIF('RENDA VARIAVEL | CORRETAGEM'!D:D,CONSOLIDADO!B10,'RENDA VARIAVEL | CORRETAGEM'!H:H)*0.75 -> 472.305 | G10: =SUMIF('RENDA VARIAVEL | ESTRUTURADAS'!I:I,CONSOLIDADO!B10,'RENDA VARIAVEL | ESTRUTURADAS'!G:G) -> 239.1 | H10: =SUMIF(CÂMBIO!G:G,CONSOLIDADO!B10,CÂMBIO!O:O)/2 -> 0 | I10: =((SUMIF('FUNDOS FECHADOS'!J:J,CONSOLIDADO!B10,'FUNDOS FECHADOS'!I:I))*0.85)+(SUMIF('SECUNDARIO FUNDOS'!D:D,CONSOLIDADO!B10,'SECUNDARIO FUNDOS'!O:O)) -> 0 | J10: =SUMIF(COE!B:B,CONSOLIDADO!B10,COE!K:K) -> 0 | K10: =SUM(E10:J10) -> 1856.905
B11: 96837 | C11: PRODUTOS | D11: JOÃO VICTOR MORAIS | E11: =(SUMIF('SECUNDÁRIO RF'!C:C,CONSOLIDADO!B11,'SECUNDÁRIO RF'!N:N)/2)+(SUMIF('PRIMARIO RF'!B:B,CONSOLIDADO!B11,'PRIMARIO RF'!U:U)) -> 0 | F11: =SUMIF('RENDA VARIAVEL | CORRETAGEM'!D:D,CONSOLIDADO!B11,'RENDA VARIAVEL | CORRETAGEM'!H:H)*0.75 -> 75 | G11: =SUMIF('RENDA VARIAVEL | ESTRUTURADAS'!I:I,CONSOLIDADO!B11,'RENDA VARIAVEL | ESTRUTURADAS'!G:G) -> 0 | H11: =SUMIF(CÂMBIO!G:G,CONSOLIDADO!B11,CÂMBIO!O:O)/2 -> 0 | I11: =((SUMIF('FUNDOS FECHADOS'!J:J,CONSOLIDADO!B11,'FUNDOS FECHADOS'!I:I))*0.85)+(SUMIF('SECUNDARIO FUNDOS'!D:D,CONSOLIDADO!B11,'SECUNDARIO FUNDOS'!O:O)) -> 106.1754 | J11: =SUMIF(COE!B:B,CONSOLIDADO!B11,COE!K:K) -> 0 | K11: =SUM(E11:J11) -> 181.1754
B12: 38675 | C12: CORPORATE | D12: LUCA BELLANDI | E12: =(SUMIF('SECUNDÁRIO RF'!C:C,CONSOLIDADO!B12,'SECUNDÁRIO RF'!N:N)/2)+(SUMIF('PRIMARIO RF'!B:B,CONSOLIDADO!B12,'PRIMARIO RF'!U:U)) -> 0 | F12: =SUMIF('RENDA VARIAVEL | CORRETAGEM'!D:D,CONSOLIDADO!B12,'RENDA VARIAVEL | CORRETAGEM'!H:H)*0.75 -> 480.9075 | G12: =SUMIF('RENDA VARIAVEL | ESTRUTURADAS'!I:I,CONSOLIDADO!B12,'RENDA VARIAVEL | ESTRUTURADAS'!G:G) -> 0 | H12: =SUMIF(CÂMBIO!G:G,CONSOLIDADO!B12,CÂMBIO!O:O)/2 -> 514.87 | I12: =((SUMIF('FUNDOS FECHADOS'!J:J,CONSOLIDADO!B12,'FUNDOS FECHADOS'!I:I))*0.85)+(SUMIF('SECUNDARIO FUNDOS'!D:D,CONSOLIDADO!B12,'SECUNDARIO FUNDOS'!O:O)) -> 3094.9186 | J12: =SUMIF(COE!B:B,CONSOLIDADO!B12,COE!K:K) -> 0 | K12: =SUM(E12:J12) -> 4090.6961
B13: 20020 | C13: PRODUTOS | D13: ALEXANDRE ACHUI | E13: =(SUMIF('SECUNDÁRIO RF'!C:C,CONSOLIDADO!B13,'SECUNDÁRIO RF'!N:N)/2)+(SUMIF('PRIMARIO RF'!B:B,CONSOLIDADO!B13,'PRIMARIO RF'!U:U)) -> 160 | F13: =SUMIF('RENDA VARIAVEL | CORRETAGEM'!D:D,CONSOLIDADO!B13,'RENDA VARIAVEL | CORRETAGEM'!H:H)*0.75 -> 105.81 | G13: =SUMIF('RENDA VARIAVEL | ESTRUTURADAS'!I:I,CONSOLIDADO!B13,'RENDA VARIAVEL | ESTRUTURADAS'!G:G) -> 0 | H13: =SUMIF(CÂMBIO!G:G,CONSOLIDADO!B13,CÂMBIO!O:O)/2 -> 45.533433 | I13: =((SUMIF('FUNDOS FECHADOS'!J:J,CONSOLIDADO!B13,'FUNDOS FECHADOS'!I:I))*0.85)+(SUMIF('SECUNDARIO FUNDOS'!D:D,CONSOLIDADO!B13,'SECUNDARIO FUNDOS'!O:O)) -> 0 | J13: =SUMIF(COE!B:B,CONSOLIDADO!B13,COE!K:K) -> 0 | K13: =SUM(E13:J13) -> 311.34343
B14: 22945 | C14: BACKOFFICE | D14: GUILHERME PRAXEDES | E14: =(SUMIF('SECUNDÁRIO RF'!C:C,CONSOLIDADO!B14,'SECUNDÁRIO RF'!N:N)/2)+(SUMIF('PRIMARIO RF'!B:B,CONSOLIDADO!B14,'PRIMARIO RF'!U:U)) -> 0 | F14: =SUMIF('RENDA VARIAVEL | CORRETAGEM'!D:D,CONSOLIDADO!B14,'RENDA VARIAVEL | CORRETAGEM'!H:H)*0.75 -> 0 | G14: =SUMIF('RENDA VARIAVEL | ESTRUTURADAS'!I:I,CONSOLIDADO!B14,'RENDA VARIAVEL | ESTRUTURADAS'!G:G) -> 0 | H14: =SUMIF(CÂMBIO!G:G,CONSOLIDADO!B14,CÂMBIO!O:O)/2 -> 0 | I14: =((SUMIF('FUNDOS FECHADOS'!J:J,CONSOLIDADO!B14,'FUNDOS FECHADOS'!I:I))*0.85)+(SUMIF('SECUNDARIO FUNDOS'!D:D,CONSOLIDADO!B14,'SECUNDARIO FUNDOS'!O:O)) -> 0 | J14: =SUMIF(COE!B:B,CONSOLIDADO!B14,COE!K:K) -> 0 | K14: =SUM(E14:J14) -> 0
B15: 24415 | C15: SP | D15: CINTIA BASSI | E15: =(SUMIF('SECUNDÁRIO RF'!C:C,CONSOLIDADO!B15,'SECUNDÁRIO RF'!N:N)/2)+(SUMIF('PRIMARIO RF'!B:B,CONSOLIDADO!B15,'PRIMARIO RF'!U:U)) -> 1328 | F15: =SUMIF('RENDA VARIAVEL | CORRETAGEM'!D:D,CONSOLIDADO!B15,'RENDA VARIAVEL | CORRETAGEM'!H:H)*0.75 -> 2415.96 | G15: =SUMIF('RENDA VARIAVEL | ESTRUTURADAS'!I:I,CONSOLIDADO!B15,'RENDA VARIAVEL | ESTRUTURADAS'!G:G) -> 9782.63 | H15: =SUMIF(CÂMBIO!G:G,CONSOLIDADO!B15,CÂMBIO!O:O)/2 -> 1478.771 | I15: =((SUMIF('FUNDOS FECHADOS'!J:J,CONSOLIDADO!B15,'FUNDOS FECHADOS'!I:I))*0.85)+(SUMIF('SECUNDARIO FUNDOS'!D:D,CONSOLIDADO!B15,'SECUNDARIO FUNDOS'!O:O)) -> 6766.8118 | J15: =SUMIF(COE!B:B,CONSOLIDADO!B15,COE!K:K) -> 0 | K15: =SUM(E15:J15) -> 21772.173
B16: 22103 | C16: SP | D16: LUCIANO FERES | E16: =(SUMIF('SECUNDÁRIO RF'!C:C,CONSOLIDADO!B16,'SECUNDÁRIO RF'!N:N)/2)+(SUMIF('PRIMARIO RF'!B:B,CONSOLIDADO!B16,'PRIMARIO RF'!U:U)) -> 147879 | F16: =SUMIF('RENDA VARIAVEL | CORRETAGEM'!D:D,CONSOLIDADO!B16,'RENDA VARIAVEL | CORRETAGEM'!H:H)*0.75 -> 9727.395 | G16: =SUMIF('RENDA VARIAVEL | ESTRUTURADAS'!I:I,CONSOLIDADO!B16,'RENDA VARIAVEL | ESTRUTURADAS'!G:G) -> 0 | H16: =SUMIF(CÂMBIO!G:G,CONSOLIDADO!B16,CÂMBIO!O:O)/2 -> 485.85 | I16: =((SUMIF('FUNDOS FECHADOS'!J:J,CONSOLIDADO!B16,'FUNDOS FECHADOS'!I:I))*0.85)+(SUMIF('SECUNDARIO FUNDOS'!D:D,CONSOLIDADO!B16,'SECUNDARIO FUNDOS'!O:O)) -> 0 | J16: =SUMIF(COE!B:B,CONSOLIDADO!B16,COE!K:K) -> 0 | K16: =SUM(E16:J16) -> 158092.24
B17: 25619 | C17: SP | D17: SERGIO FREIRE | E17: =(SUMIF('SECUNDÁRIO RF'!C:C,CONSOLIDADO!B17,'SECUNDÁRIO RF'!N:N)/2)+(SUMIF('PRIMARIO RF'!B:B,CONSOLIDADO!B17,'PRIMARIO RF'!U:U)) -> 20685.5 | F17: =SUMIF('RENDA VARIAVEL | CORRETAGEM'!D:D,CONSOLIDADO!B17,'RENDA VARIAVEL | CORRETAGEM'!H:H)*0.75 -> 6339.585 | G17: =SUMIF('RENDA VARIAVEL | ESTRUTURADAS'!I:I,CONSOLIDADO!B17,'RENDA VARIAVEL | ESTRUTURADAS'!G:G) -> 923.03 | H17: =SUMIF(CÂMBIO!G:G,CONSOLIDADO!B17,CÂMBIO!O:O)/2 -> 64.985749 | I17: =((SUMIF('FUNDOS FECHADOS'!J:J,CONSOLIDADO!B17,'FUNDOS FECHADOS'!I:I))*0.85)+(SUMIF('SECUNDARIO FUNDOS'!D:D,CONSOLIDADO!B17,'SECUNDARIO FUNDOS'!O:O)) -> 28143.293 | J17: =SUMIF(COE!B:B,CONSOLIDADO!B17,COE!K:K) -> 0 | K17: =SUM(E17:J17) -> 56156.394
B18: 99701 | C18: PRODUTOS | D18: ARTUR BRITO | E18: =(SUMIF('SECUNDÁRIO RF'!C:C,CONSOLIDADO!B18,'SECUNDÁRIO RF'!N:N)/2)+(SUMIF('PRIMARIO RF'!B:B,CONSOLIDADO!B18,'PRIMARIO RF'!U:U)) -> 0 | F18: =SUMIF('RENDA VARIAVEL | CORRETAGEM'!D:D,CONSOLIDADO!B18,'RENDA VARIAVEL | CORRETAGEM'!H:H)*0.75 -> 0 | G18: =SUMIF('RENDA VARIAVEL | ESTRUTURADAS'!I:I,CONSOLIDADO!B18,'RENDA VARIAVEL | ESTRUTURADAS'!G:G) -> 0 | H18: =SUMIF(CÂMBIO!G:G,CONSOLIDADO!B18,CÂMBIO!O:O)/2 -> 0 | I18: =((SUMIF('FUNDOS FECHADOS'!J:J,CONSOLIDADO!B18,'FUNDOS FECHADOS'!I:I))*0.85)+(SUMIF('SECUNDARIO FUNDOS'!D:D,CONSOLIDADO!B18,'SECUNDARIO FUNDOS'!O:O)) -> 0 | J18: =SUMIF(COE!B:B,CONSOLIDADO!B18,COE!K:K) -> 0 | K18: =SUM(E18:J18) -> 0
... B38: 21468 | C38: ANYWHERE | D38: CANDIDO GONÇALVES | E38: =(SUMIF('SECUNDÁRIO RF'!C:C,CONSOLIDADO!B38,'SECUNDÁRIO RF'!N:N)/2)+(SUMIF('PRIMARIO RF'!B:B,CONSOLIDADO!B38,'PRIMARIO RF'!U:U)) -> 10712 | F38: =SUMIF('RENDA VARIAVEL | CORRETAGEM'!D:D,CONSOLIDADO!B38,'RENDA VARIAVEL | CORRETAGEM'!H:H)*0.75 -> 3064.545 | G38: =SUMIF('RENDA VARIAVEL | ESTRUTURADAS'!I:I,CONSOLIDADO!B38,'RENDA VARIAVEL | ESTRUTURADAS'!G:G) -> 604.74 | H38: =SUMIF(CÂMBIO!G:G,CONSOLIDADO!B38,CÂMBIO!O:O)/2 -> 652.58735 | I38: =((SUMIF('FUNDOS FECHADOS'!J:J,CONSOLIDADO!B38,'FUNDOS FECHADOS'!I:I))*0.85)+(SUMIF('SECUNDARIO FUNDOS'!D:D,CONSOLIDADO!B38,'SECUNDARIO FUNDOS'!O:O)) -> 3319.5788 | J38: =SUMIF(COE!B:B,CONSOLIDADO!B38,COE!K:K) -> 335 | K38: =SUM(E38:J38) -> 18688.451
D40: TOTAL | E40: =SUM(E7:E38) -> 389722 | F40: =SUM(F7:F38) -> 91568.67 | G40: =SUM(G7:G38) -> 25862.86 | H40: =SUM(H7:H38) -> 11673.012 | I40: =SUM(I7:I38) -> 77617.221 | J40: =SUM(J7:J38) -> 1270.5 | K40: =SUM(E40:J40) -> 597714.26 | L40: 350000 | M40: =L40+K40 -> 947714.26

Sheet CONSOLIDADO (3)
B2: DATA BASE
B3: 46077
D5: PRODUTOS
B6: Assessor | C6: Equipe | D6: Nome Assessor | E6: Renda Fixa (Primário + Secundário) | F6: Renda Variavel (Corretagem) | G6: Renda Variavel (PE) | H6: Câmbio | I6: Fundos Fechados (Primário + Secundário) | J6: COE | K6: Receita Geral
B7: 22103 | C7: SP | D7: LUCIANO FERES | E7: 147879 | F7: 9727.395 | G7: 0 | H7: 485.85 | I7: 0 | J7: 0 | K7: 158092.24 | L7: =(K7+K8+K10+K14+K23+K28)/K40 -> 0.52786455
B8: 49894 | C8: SP | D8: VICTOR GODOY | E8: 32617 | F8: 4720.23 | G8: 0 | H8: 701.29095 | I8: 33911.731 | J8: 0 | K8: 71950.252
B9: 41072 | C9: BARRA | D9: ERICK VIANNA | E9: 24389.5 | F9: 30238.627 | G9: 3399.93 | H9: 0 | I9: 0 | J9: 0 | K9: 58028.057
B10: 25619 | C10: SP | D10: SERGIO FREIRE | E10: 20685.5 | F10: 6339.585 | G10: 923.03 | H10: 64.985749 | I10: 28143.293 | J10: 0 | K10: 56156.394
B11: 71997 | C11: BARRA | D11: CAE BRANDÃO | E11: 36481.5 | F11: 1409.655 | G11: 0 | H11: 3123.79 | I11: 0 | J11: 0 | K11: 41014.945
B12: 69519 | C12: LEBLON | D12: NICOLAS KERSUL | E12: 19018.5 | F12: 5171.4825 | G12: 3451.1 | H12: 161.33335 | I12: 0 | J12: 0 | K12: 27802.416
B13: 22674 | C13: LEBLON | D13: RAFAEL PEREIRA | E13: 22039 | F13: 3827.5725 | G13: 720.91 | H13: 0 | I13: 0 | J13: 0 | K13: 26587.483
B14: 24415 | C14: SP | D14: CINTIA BASSI | E14: 1328 | F14: 2415.96 | G14: 9782.63 | H14: 1478.771 | I14: 6766.8118 | J14: 0 | K14: 21772.173
B15: 23410 | C15: LEBLON | D15: PATRICIA LANGONI | E15: 17092.5 | F15: 3341.4825 | G15: 1096.57 | H15: 158.51435 | I15: 0 | J15: 0 | K15: 21689.067
B16: 38517 | C16: LEBLON | D16: PEDRO GONÇALVES | E16: 17635 | F16: 1863.8175 | G16: 0 | H16: 738.05699 | I16: 0 | J16: 0 | K16: 20236.874
B17: 21468 | C17: ANYWHERE | D17: CANDIDO GONÇALVES | E17: 10712 | F17: 3064.545 | G17: 604.74 | H17: 652.58735 | I17: 3319.5788 | J17: 335 | K17: 18688.451
B18: 21559 | C18: BARRA | D18: DIOGO LUZ | E18: 10747.5 | F18: 2608.9275 | G18: 704.17 | H18: 0 | I18: 0 | J18: 0 | K18: 14060.597
B19: 23648 | C19: BARRA | D19: BRUNO TORRES | E19: 8128 | F19: 4157.985 | G19: 242.93 | H19: 0 | I19: 556.2738 | J19: 935.5 | K19: 14020.689
... B38: 99742 | C38: BACKOFFICE | D38: BERNARDO LASMAR | E38: 0 | F38: 0 | G38: 0 | H38: 0 | I38: 0 | J38: 0 | K38: 0
D40: TOTAL | E40: =SUM(E7:E38) -> 389722 | F40: =SUM(F7:F38) -> 91568.67 | G40: =SUM(G7:G38) -> 25862.86 | H40: =SUM(H7:H38) -> 11673.012 | I40: =SUM(I7:I38) -> 77617.221 | J40: =SUM(J7:J38) -> 1270.5 | K40: =SUM(E40:J40) -> 597714.26 | L40: 350000 | M40: =L40+K40 -> 947714.26

Sheet SECUNDÁRIO RF
B2: Data | C2: Cód. ssessor | D2: Cód. conta | E2: Tipo ativo | F2: Ticker | G2: Nome papel | H2: Indexador | I2: Vencimento | J2: Tipo juros | K2: Tipo operação | L2: Quantidade | M2: Volume | N2: Receita a dividir | O2: PU Cliente | P2: PU TMR | Q2: Taxa Cliente | R2: Taxa TMR
B3: 46055 | C3: 22674 | D3: 8014791 | E3: EB s/ Liquidez | F3: CDB2223IBZF | G3: CDB AGIBANK - ABR/2026 | H3: IPC-A | I3: 46125 | J3: Vencimento | K3: RESGATE | L3: 22 | M3: -33788 | N3: 14 | O3: 1535.8 | P3: 1536.5 | Q3: 10.75 | R3: 10.5
B4: 46055 | C4: 23410 | D4: 284340 | E4: Título Público | F4: 760199 | G4: NTN-B - MAI/2029 | H4: IPC-A | I4: 47253 | J4: Semestral | K4: APLICAÇÃO | L4: 4 | M4: 18088 | N4: 247 | O4: 4521.9 | P4: 4460.1 | Q4: 7.09 | R4: 7.59
B5: 46055 | C5: 23410 | D5: 3090926 | E5: Título Público | F5: 760199 | G5: NTN-B - MAI/2029 | H5: IPC-A | I5: 47253 | J5: Semestral | K5: APLICAÇÃO | L5: 9 | M5: 40697 | N5: 556 | O5: 4521.9 | P5: 4460.1 | Q5: 7.09 | R5: 7.59
B6: 46055 | C6: 23410 | D6: 6162039 | E6: Título Público | F6: 760199 | G6: NTN-B - AGO/2030 | H6: IPC-A | I6: 47710 | J6: Semestral | K6: APLICAÇÃO | L6: 26 | M6: 118002 | N6: 1904 | O6: 4538.5 | P6: 4465.3 | Q6: 7.13 | R6: 7.58
B7: 46055 | C7: 23410 | D7: 8449786 | E7: Título Público | F7: 760199 | G7: NTN-B - AGO/2028 | H7: IPC-A | I7: 46980 | J7: Semestral | K7: RESGATE | L7: 7 | M7: -31581 | N7: 169 | O7: 4511.6 | P7: 4535.7 | Q7: 8.14 | R7: 7.89
B8: 46055 | C8: 23410 | D8: 11000943 | E8: Título Público | F8: 760199 | G8: NTN-B - AGO/2032 | H8: IPC-A | I8: 48441 | J8: Semestral | K8: APLICAÇÃO | L8: 11 | M8: 49324 | N8: 1199 | O8: 4484 | P8: 4375 | Q8: 7.07 | R8: 7.57
B9: 46055 | C9: 23410 | D9: 11000943 | E9: Título Público | F9: 760199 | G9: NTN-B - MAI/2035 | H9: IPC-A | I9: 49444 | J9: Semestral | K9: APLICAÇÃO | L9: 12 | M9: 52251 | N9: 1352 | O9: 4354.3 | P9: 4241.6 | Q9: 7.04 | R9: 7.44
B10: 46055 | C10: 23410 | D10: 11175225 | E10: Título Público | F10: 760199 | G10: NTN-B - AGO/2032 | H10: IPC-A | I10: 48441 | J10: Semestral | K10: APLICAÇÃO | L10: 26 | M10: 116585 | N10: 2834 | O10: 4484 | P10: 4375 | Q10: 7.07 | R10: 7.57
B11: 46055 | C11: 23410 | D11: 13051869 | E11: Título Público | F11: 760199 | G11: NTN-B - AGO/2030 | H11: IPC-A | I11: 47710 | J11: Semestral | K11: APLICAÇÃO | L11: 7 | M11: 31393 | N11: 136 | O11: 4484.7 | P11: 4465.3 | Q11: 7.46 | R11: 7.58
B12: 46055 | C12: 25104 | D12: 401402 | E12: EB s/ Liquidez | F12: 25G04858539 | G12: LCA BANCO JOHN DEERE S.A. - JUL/2029 | H12: CDI | I12: 47323 | J12: Vencimento | K12: APLICAÇÃO | L12: 40 | M12: 43453 | N12: 537 | O12: 1086.3 | P12: 1072.9 | Q12: 93 | R12: 96
B13: 46055 | C13: 25104 | D13: 6035839 | E13: EB s/ Liquidez | F13: 24L02792805 | G13: LCD BNDES - DEZ/2029 | H13: CDI | I13: 47457 | J13: Vencimento | K13: RESGATE | L13: 5 | M13: -58680 | N13: 679 | O13: 11735.9 | P13: 11871.7 | Q13: 95 | R13: 92.5
B14: 46055 | C14: 25619 | D14: 5375448 | E14: Crédito Privado | F14: 25E0053938 | G14: CRI JHSF - MAI/2032 | H14: PRE | I14: 48351 | J14: Vencimento | K14: APLICAÇÃO | L14: 100 | M14: 104143 | N14: 185 | O14: 1041.4 | P14: 1039.6 | Q14: 13.85 | R14: 13.9
... B285: 46076 | C285: 72444 | D285: 3187997 | E285: Crédito Privado | F285: CRA024001E7 | G285: CRA BANCO ABC - FEV/2034 | H285: CDI | I285: 48985 | J285: Semestral | K285: RESGATE | L285: 75 | M285: -76752 | N285: 981 | O285: 1023.4 | P285: 1036.4 | Q285: 104 | R285: 102

Sheet PRIMARIO RF
B2: Código aai | C2: Nome Assessor | D2: Conta XP | E2: Nome Cliente | F2: Valor Solicitado | G2: Taxa Solicitada | H2: Opção Pessoa Vinculada | I2: Status da Solicitação da Reserva | J2: Investidor Qualificado | K2: Investidor Profissional | L2: Status do Resultado da Oferta | M2: Tipo de Investidor | N2: Financeiro a liquidar | O2: Quantidade a liquidar | P2: Data da liquidação prevista | Q2: Volume total da emissão | R2: Taxa final da oferta | S2: PU da Liquidação | T2: ROA | U2: RECEITA
B3: 22103 | C3: LUCIANO FERES | D3: 3240793 | E3: MONICA ANDRES GARCIA MOREJON | F3: 1500000 | G3: 10 | H3: Investidor Não vinculado | I3: Solicitado | J3: Sim | K3: Sim | M3: Publico Institucional Não Vinculado | N3: 0 | P3: 46080 | Q3: 0 | S3: 1000 | T3: 0.0325 | U3: =T3*F3 -> 48750
B4: 22103 | C4: LUCIANO FERES | D4: 2010261 | E4: FLAVIO HACHEM | F4: 1000000 | G4: 10 | H4: Investidor Não vinculado | I4: Solicitado | J4: Sim | K4: Sim | M4: Publico Institucional Não Vinculado | N4: 0 | P4: 46080 | Q4: 0 | S4: 1000 | T4: 0.0325 | U4: =T4*F4 -> 32500
B5: 71997 | C5: CAE BRANDÃO | D5: 2730105 | E5: RODOLFO RANIEIRI POMBO | F5: 1000000 | G5: 10 | H5: Investidor Não vinculado | I5: Solicitado | J5: Sim | K5: Sim | M5: Publico Institucional Não Vinculado | N5: 0 | P5: 46080 | Q5: 0 | S5: 1000 | T5: 0.0325 | U5: =T5*F5 -> 32500
B6: 22103 | C6: LUCIANO FERES | D6: 52162 | E6: JOSE VICENTE PEREIRA JUSTO CARNERO | F6: 800000 | G6: 10 | H6: Investidor Não vinculado | I6: Solicitado | J6: Sim | K6: Sim | M6: Publico Institucional Não Vinculado | N6: 0 | P6: 46080 | Q6: 0 | S6: 1000 | T6: 0.0325 | U6: =T6*F6 -> 26000
B7: 22103 | C7: LUCIANO FERES | D7: 2217992 | E7: RODRIGO CHOHFI | F7: 500000 | G7: 10 | H7: Investidor Não vinculado | I7: Solicitado | J7: Sim | K7: Sim | M7: Publico Institucional Não Vinculado | N7: 0 | P7: 46080 | Q7: 0 | S7: 1000 | T7: 0.0325 | U7: =T7*F7 -> 16250
B8: 25619 | C8: SERGIO FREIRE | D8: 5714703 | E8: EDUARDO AUGUSTO RIBEIRO MAGALHAES | F8: 500000 | G8: 10 | H8: Investidor Não vinculado | I8: Solicitado | J8: Sim | K8: Sim | M8: Publico Institucional Não Vinculado | N8: 0 | P8: 46080 | Q8: 0 | S8: 1000 | T8: 0.0325 | U8: =T8*F8 -> 16250
B9: 69519 | C9: NICOLAS KERSUL | D9: 366105 | E9: EVANDRO MENDES DA SILVA JUNIOR | F9: 300000 | G9: 10 | H9: Investidor Não vinculado | I9: Solicitado | J9: Sim | K9: Não | M9: Publico Institucional Não Vinculado | N9: 0 | P9: 46080 | Q9: 0 | S9: 1000 | T9: 0.0325 | U9: =T9*F9 -> 9750
B10: 41072 | C10: ERICK VIANNA | D10: 3381519 | E10: MARIO ASSIS GONCALVES FILHO | F10: 300000 | G10: 10 | H10: Investidor Não vinculado | I10: Solicitado | J10: Sim | K10: Não | M10: Publico Institucional Não Vinculado | N10: 0 | P10: 46080 | Q10: 0 | S10: 1000 | T10: 0.0325 | U10: =T10*F10 -> 9750
B11: 22103 | C11: LUCIANO FERES | D11: 2475980 | E11: BETINA ZARZUR HACHEM | F11: 300000 | G11: 10 | H11: Investidor Não vinculado | I11: Solicitado | J11: Sim | K11: Sim | M11: Publico Institucional Não Vinculado | N11: 0 | P11: 46080 | Q11: 0 | S11: 1000 | T11: 0.0325 | U11: =T11*F11 -> 9750
B12: 22103 | C12: LUCIANO FERES | D12: 15496606 | E12: FABIO HENRIQUE FIGUEIREDO VEGGIATO | F12: 300000 | G12: 10 | H12: Investidor Não vinculado | I12: Solicitado | J12: Sim | K12: Não | M12: Publico Institucional Não Vinculado | N12: 0 | P12: 46080 | Q12: 0 | S12: 1000 | T12: 0.0325 | U12: =T12*F12 -> 9750
B13: 49894 | C13: VICTOR GODOY | D13: 16697783 | E13: LEONEL AUGUSTO PIRES GRANJO | F13: 300000 | G13: 10 | H13: Investidor Não vinculado | I13: Solicitado | J13: Sim | K13: Sim | M13: Publico Institucional Não Vinculado | N13: 0 | P13: 46080 | Q13: 0 | S13: 1000 | T13: 0.0325 | U13: =T13*F13 -> 9750
B14: 41072 | C14: ERICK VIANNA | D14: 11712403 | E14: REGINA TREIGER CHERQUES | F14: 250000 | G14: 10 | H14: Investidor Não vinculado | I14: Solicitado | J14: Sim | K14: Não | M14: Publico Institucional Não Vinculado | N14: 0 | P14: 46080 | Q14: 0 | S14: 1000 | T14: 0.0325 | U14: =T14*F14 -> 8125
... B68: 40901 | C68: JOAO PEDRO GUIMARAES | D68: 11610966 | E68: NICOLA YURI BALBONI FRANCINETTI | F68: 10000 | G68: 10 | H68: Investidor Não vinculado | I68: Solicitado | J68: Sim | K68: Não | M68: Publico Institucional Não Vinculado | N68: 0 | P68: 46080 | Q68: 0 | S68: 1000 | T68: 0.0325 | U68: =T68*F68 -> 325

Sheet RENDA VARIAVEL | CORRETAGEM
B2: Conta | C2: Suitability | D2: Cod | E2: Matriz | F2: Ativo | G2: Qtd | H2: Corretagem | I2: Volume Negociado | J2: Produto | K2: Canal | L2: Tipo de Corretagem | M2: Mercado | N2: Lado | O2: Data
B3: 3178778 | C3: AGRESSIVO | D3: 22103 | E3: SOMUS CAPITAL | F3: UGPA3 | G3: 37200 | H3: 5034.19 | I3: 1001796 | J3: Ações | K3: Mesa | L3: Variavel | M3: BOV | N3: Venda | O3: 46062
B4: 11733006 | C4: AGRESSIVO | D4: 41072 | E4: SOMUS CAPITAL | F4: ENEV3 | G4: 40000 | H4: 3154.78 | I4: 757000 | J4: Ações | K4: Push | L4: Variavel | M4: BOV | N4: Venda | O4: 46063
B5: 11733006 | C5: AGRESSIVO | D5: 41072 | E5: SOMUS CAPITAL | F5: SUZB3 | G5: 14400 | H5: 3085.2 | I5: 740304 | J5: Ações | K5: Push | L5: Variavel | M5: BOV | N5: Compra | O5: 46063
B6: 11733006 | C6: AGRESSIVO | D6: 41072 | E6: SOMUS CAPITAL | F6: SUZB3 | G6: 14400 | H6: 3085.15 | I6: 740293 | J6: Ações | K6: Push | L6: Variavel | M6: BOV | N6: Venda | O6: 46063
B7: 11733006 | C7: AGRESSIVO | D7: 41072 | E7: SOMUS CAPITAL | F7: ENEV3 | G7: 40000 | H7: 3037.87 | I7: 728952 | J7: Ações | K7: Push | L7: Variavel | M7: BOV | N7: Compra | O7: 46063
B8: 16469589 | C8: AGRESSIVO | D8: 41072 | E8: SOMUS CAPITAL | F8: BPAC11 | G8: 9200 | H8: 2760.6 | I8: 548858 | J8: Ações | K8: Push | L8: Variavel | M8: BOV | N8: Compra | O8: 46063
B9: 11733006 | C9: AGRESSIVO | D9: 41072 | E9: SOMUS CAPITAL | F9: MELI34 | G9: 6000 | H9: 2676.18 | I9: 531900 | J9: BDR | K9: Push | L9: Variavel | M9: BOV | N9: Compra | O9: 46065
B10: 11733006 | C10: AGRESSIVO | D10: 41072 | E10: SOMUS CAPITAL | F10: MELI34 | G10: 6000 | H10: 2635.39 | I10: 522036.87 | J10: BDR | K10: Push | L10: Variavel | M10: BOV | N10: Venda | O10: 46071
B11: 16469589 | C11: AGRESSIVO | D11: 41072 | E11: SOMUS CAPITAL | F11: MELI34 | G11: 4000 | H11: 1795.96 | I11: 356000 | J11: BDR | K11: Push | L11: Variavel | M11: BOV | N11: Compra | O11: 46065
B12: 16777030 | C12: AGRESSIVO | D12: 27086 | E12: SOMUS CAPITAL | F12: KLBN11 | G12: 16100 | H12: 1628.42 | I12: 320641 | J12: Ações | K12: Push | L12: Variavel | M12: BOV | N12: Venda | O12: 46062
B13: 16469589 | C13: AGRESSIVO | D13: 41072 | E13: SOMUS CAPITAL | F13: RENT3 | G13: 5800 | H13: 1489.92 | I13: 296225 | J13: Ações | K13: Push | L13: Variavel | M13: BOV | N13: Venda | O13: 46063
B14: 11733006 | C14: AGRESSIVO | D14: 41072 | E14: SOMUS CAPITAL | F14: MELI34 | G14: 3100 | H14: 1368.5 | I14: 271994 | J14: Estruturadas | K14: Estruturadas | L14: Variavel | M14: BOV | N14: Compra | O14: 46065
... B3040: 310157 | C3040: AGRESSIVO | D3040: 68542 | E3040: SOMUS CAPITAL | F3040: PETR4 | G3040: 1 | H3040: 0.01 | I3040: 36.95 | J3040: Ações | K3040: Mesa | L3040: Variavel | M3040: BOV | N3040: Compra | O3040: 46055

Sheet RENDA VARIAVEL | ESTRUTURADAS
B2: Cliente | C2: Data | D2: Origem | E2: Ativo | F2: Estratégia | G2: Comissão | H2: Cod Matriz | I2: Cod | J2: Status da Operação
B3: 2033851 | C3: 46059 | D3: MESA | E3: SMAL11 | F3: POP | G3: 81.28 | H3: 73037 | I3: 24415 | J3: Totalmente executado
B4: 3436001 | C4: 46056 | D4: MESA | E4: NÃO ENCONTRADO | F4: Smart Coupon | G4: 100.93 | H4: 73037 | I4: 21468 | J4: Totalmente executado
B5: 357627 | C5: 46056 | D5: MESA | E5: NÃO ENCONTRADO | F5: Smart Coupon | G5: 100.93 | H5: 73037 | I5: 72444 | J5: Totalmente executado
B6: 4868551 | C6: 46064 | D6: MESA | E6: LREN3 | F6: Smart Coupon | G6: 106.31 | H6: 73037 | I6: 22674 | J6: Totalmente executado
B7: 4257721 | C7: 46064 | D7: MESA | E7: NÃO ENCONTRADO | F7: Smart Coupon | G7: 112.43 | H7: 73037 | I7: 22674 | J7: Totalmente executado
B8: 4406804 | C8: 46066 | D8: MESA | E8: MELI34 | F8: Smart Coupon | G8: 119.55 | H8: 73037 | I8: 96553 | J8: Totalmente executado
B9: 9650565 | C9: 46066 | D9: MESA | E9: MELI34 | F9: Smart Coupon | G9: 119.55 | H9: 73037 | I9: 96553 | J9: Totalmente executado
B10: 2742454 | C10: 46056 | D10: MESA | E10: ENEV3 | F10: Smart Coupon | G10: 136.95 | H10: 73037 | I10: 22674 | J10: Totalmente executado
B11: 3430907 | C11: 46055 | D11: MESA | E11: NÃO ENCONTRADO | F11: Smart Coupon | G11: 139.06 | H11: 73037 | I11: 21468 | J11: Totalmente executado
B12: 293951 | C12: 46071 | D12: MESA | E12: NÃO ENCONTRADO | F12: Smart Coupon | G12: 141.62 | H12: 73037 | I12: 25619 | J12: Totalmente executado
B13: 11010432 | C13: 46065 | D13: MESA | E13: TOTS3 | F13: Smart Coupon | G13: 160.66 | H13: 73037 | I13: 25619 | J13: Totalmente executado
B14: 2727239 | C14: 46057 | D14: MESA | E14: ENEV3 | F14: Smart Coupon | G14: 168.15 | H14: 73037 | I14: 21559 | J14: Totalmente executado
... B40: 4610798 | C40: 46056 | D40: MESA | E40: VALE3 | F40: Collar UI sob custódia | G40: 5215.78 | H40: 73037 | I40: 24415 | J40: Totalmente executado

Sheet CÂMBIO
B2: Data | C2: Código Cliente | D2: CD_ESCRITORIO | E2: NM_ESCRITORIO | F2: TP_PESSOA | G2: ssessor | H2: Lado Cliente | I2: Moeda | J2: Valor em Moeda Estrangeira | K2: Taxa Custo | L2: Taxa Cliente | M2: Valor em Reais | N2: Spread_Medio | O2: Receita a dividir | P2: DT_MN_CLI | Q2: DT_ME_CLI
B3: 46055 | C3: 14522139 | D3: 73037 | E3: SOMUS CAPITAL ASSESSOR DE INVESTIMENTOS LTDA | F3: PJ | G3: 23410 | H3: Envio | I3: 220 | J3: 753 | K3: 5.2625 | L3: 5.3354 | M3: 4017.56 | N3: 0.013663442 | O3: 54.8937 | P3: 46055 | Q3: 46055
B4: 46055 | C4: 18387496 | D4: 73037 | E4: SOMUS CAPITAL ASSESSOR DE INVESTIMENTOS LTDA | F4: PJ | G4: 49894 | H4: Recebimento | I4: 220 | J4: 16500 | K4: 5.2361 | L4: 5.1735 | M4: 85362.75 | N4: 0.012100126 | O4: 1032.9 | P4: 46055 | Q4: 46055
B5: 46055 | C5: 8971607 | D5: 73037 | E5: SOMUS CAPITAL ASSESSOR DE INVESTIMENTOS LTDA | F5: PJ | G5: 38517 | H5: Recebimento | I5: 220 | J5: 2366.33 | K5: 10.5032 | L5: 10.421 | M5: 12329.77 | N5: 0.0078879138 | O5: 97.256163 | P5: 46055 | Q5: 46055
B6: 46055 | C6: 8971607 | D6: 73037 | E6: SOMUS CAPITAL ASSESSOR DE INVESTIMENTOS LTDA | F6: PJ | G6: 38517 | H6: Recebimento | I6: 978 | J6: 11.29 | K6: 6.208 | L6: 6.1544 | M6: 69.48 | N6: 0.0087096143 | O6: 0.605144 | P6: 46055 | Q6: 46055
B7: 46056 | C7: 17743490 | D7: 73037 | E7: SOMUS CAPITAL ASSESSOR DE INVESTIMENTOS LTDA | F7: PJ | G7: 27086 | H7: Recebimento | I7: 220 | J7: 3500 | K7: 5.2036 | L7: 5.0995 | M7: 17848.25 | N7: 0.020413766 | O7: 364.35 | P7: 46056 | Q7: 46056
B8: 46057 | C8: 2240415 | D8: 73037 | E8: SOMUS CAPITAL ASSESSOR DE INVESTIMENTOS LTDA | F8: PF | G8: 71881 | H8: Envio | I8: 220 | J8: 6315 | K8: 5.2413 | L8: 5.262767 | M8: 33234.37 | N8: 0.0040790334 | O8: 135.5641 | P8: 46057 | Q8: 46057
B9: 46057 | C9: 3366029 | D9: 73037 | E9: SOMUS CAPITAL ASSESSOR DE INVESTIMENTOS LTDA | F9: PF | G9: 37111 | H9: Envio | I9: 978 | J9: 780.33 | K9: 6.172 | L9: 6.190817 | M9: 4830.88 | N9: 0.0030395021 | O9: 14.68347 | P9: 46057 | Q9: 46057
B10: 46057 | C10: 390738 | D10: 73037 | E10: SOMUS CAPITAL ASSESSOR DE INVESTIMENTOS LTDA | F10: PF | G10: 20020 | H10: Envio | I10: 220 | J10: 1875.81 | K10: 5.2453 | L10: 5.273 | M10: 9891.15 | N10: 0.0052531745 | O10: 51.959937 | P10: 46057 | Q10: 46057
B11: 46057 | C11: 5704052 | D11: 73037 | E11: SOMUS CAPITAL ASSESSOR DE INVESTIMENTOS LTDA | F11: PJ | G11: 72444 | H11: Recebimento | I11: 220 | J11: 1896.1 | K11: 5.2227 | L11: 5.186269 | M11: 9833.68 | N11: 0.0070245136 | O11: 69.076819 | P11: 46057 | Q11: 46057
B12: 46057 | C12: 8971607 | D12: 73037 | E12: SOMUS CAPITAL ASSESSOR DE INVESTIMENTOS LTDA | F12: PJ | G12: 38517 | H12: Recebimento | I12: 978 | J12: 3000 | K12: 6.1634 | L12: 6.104538 | M12: 18313.61 | N12: 0.009642337 | O12: 176.586 | P12: 46057 | Q12: 46057
B13: 46058 | C13: 16587500 | D13: 73037 | E13: SOMUS CAPITAL ASSESSOR DE INVESTIMENTOS LTDA | F13: PJ | G13: 49894 | H13: Recebimento | I13: 220 | J13: 4158.06 | K13: 5.2615 | L13: 5.18 | M13: 21538.75 | N13: 0.015733591 | O13: 338.88189 | P13: 46058 | Q13: 46058
B14: 46058 | C14: 17374205 | D14: 73037 | E14: SOMUS CAPITAL ASSESSOR DE INVESTIMENTOS LTDA | F14: PJ | G14: 38675 | H14: Recebimento | I14: 220 | J14: 8000 | K14: 10.4999 | L14: 10.242465 | M14: 40969.86 | N14: 0.025134086 | O14: 1029.74 | P14: 46058 | Q14: 46058
... B49: 46076 | C49: 8971607 | D49: 73037 | E49: SOMUS CAPITAL ASSESSOR DE INVESTIMENTOS LTDA | F49: PJ | G49: 38517 | H49: Recebimento | I49: 220 | J49: 3231.25 | K49: 5.1742 | L49: 5.1214 | M49: 16548.52 | N49: 0.010309683 | O49: 170.61 | P49: 46076 | Q49: 46076

Sheet FUNDOS FECHADOS
B2: Marca | C2: Código Oferta | D2: Ativo | E2: Nome Oferta | F2: Status Oferta | G2: Data Liquidação | H2: Fee | I2: Receita | J2: Assessor | K2: Cliente | L2: Oferta por Quantidade | M2: Valor/Qtde Reserva | N2: Preço Solicitado | O2: Valor/Qtde Exercido | P2: Modalidade | Q2: Status Reserva | R2: Status Push | S2: Erros | T2: Validação de Garantia
B3: XP | C3: 1478 | D3: KINSOP | E3: 1ª Emissão Subclasse A - Kinea Special Opportunities FIF MM CP RL | F3: Ativo | G3: 46084 | H3: 0.015 | I3: =H3*M3 -> 750 | J3: 25619 | K3: 15974702 | L3: Sim | M3: 50000 | N3: 1000 | P3: Reserva condicionada ao valor mínimo da oferta - NÃO VINCULADO | Q3: Solicitado | R3: Não enviado | T3: Sim
B4: XP | C4: 1504 | D4: JIVEQ2 | E4: 1ª Emissão JiveMauá BossaNova Crédito Securitizado II FIDC RL (2ª Liquidação) | F4: Ativo | G4: 46085 | H4: 0.015 | I4: =H4*M4 -> 1650.618 | J4: 49894 | K4: 16885841 | L4: Sim | M4: 110041.2 | N4: 101.89 | P4: Reserva condicionada ao valor mínimo da oferta - Não Vinculado | Q4: Solicitado | R4: Aprovado | T4: Sim
B5: XP | C5: 1504 | D5: JIVEQ2 | E5: 1ª Emissão JiveMauá BossaNova Crédito Securitizado II FIDC RL (2ª Liquidação) | F5: Ativo | G5: 46085 | H5: 0.015 | I5: =H5*M5 -> 1650.618 | J5: 49894 | K5: 18365289 | L5: Sim | M5: 110041.2 | N5: 101.89 | P5: Reserva condicionada ao valor mínimo da oferta - Não Vinculado | Q5: Solicitado | R5: Aprovado | T5: Sim
B6: XP | C6: 1509 | D6: BGRLOG | E6: Oferta Secundária BGR Galpões Logísticos I Feeder FII | F6: Ativo | G6: 46086 | H6: 0.015 | I6: =H6*M6 -> 156 | J6: 49894 | K6: 7106317 | L6: Sim | M6: 10400 | N6: 104 | P6: Solicitação de Compra de Cotas - Não Vinculado | Q6: Solicitado | R6: Aprovado | T6: Sim
B7: XP | C7: 1509 | D7: BGRLOG | E7: Oferta Secundária BGR Galpões Logísticos I Feeder FII | F7: Ativo | G7: 46086 | H7: 0.015 | I7: =H7*M7 -> 1560 | J7: 49894 | K7: 3566334 | L7: Sim | M7: 104000 | N7: 104 | P7: Solicitação de Compra de Cotas - Não Vinculado | Q7: Solicitado | R7: Aprovado | T7: Sim
B8: XP | C8: 1509 | D8: BGRLOG | E8: Oferta Secundária BGR Galpões Logísticos I Feeder FII | F8: Ativo | G8: 46086 | H8: 0.015 | I8: =H8*M8 -> 1201.2 | J8: 49894 | K8: 15055794 | L8: Sim | M8: 80080 | N8: 104 | P8: Solicitação de Compra de Cotas - Não Vinculado | Q8: Solicitado | R8: Aprovado | T8: Sim
B9: XP | C9: 1504 | D9: JIVEQ2 | E9: 1ª Emissão JiveMauá BossaNova Crédito Securitizado II FIDC RL (2ª Liquidação) | F9: Ativo | G9: 46085 | H9: 0.015 | I9: =H9*M9 -> 1222.68 | J9: 49894 | K9: 15055794 | L9: Sim | M9: 81512 | N9: 101.89 | P9: Reserva condicionada ao valor mínimo da oferta - Não Vinculado | Q9: Solicitado | R9: Aprovado | T9: Sim
B10: XP | C10: 1478 | D10: KINSOP | E10: 1ª Emissão Subclasse A - Kinea Special Opportunities FIF MM CP RL | F10: Ativo | G10: 46084 | H10: 0.015 | I10: =H10*M10 -> 750 | J10: 49894 | K10: 535922 | L10: Sim | M10: 50000 | N10: 1000 | P10: Reserva condicionada ao valor mínimo da oferta - NÃO VINCULADO | Q10: Solicitado | R10: Aprovado | T10: Sim

Sheet SECUNDARIO FUNDOS
B2: CLIENTE | C2: CONTA | D2: ssessor | E2: ATIVO | F2: DATA | G2: HORA | H2: TIPO | I2: ORIGEM | J2: QUANTIDADE | K2: QTD EXECUTADA | L2: VALOR EXECUTADO (R$) | M2: STATUS | N2: CORRETAGEM | O2: RECEITA
B3: CARLOS HENRIQUE SENNA MEDEIROS | C3: 90566 | D3: 25619 | E3: JHSF Capital Malls Feeder FII RL | F3: 46076 | G3: 14:52:44 | H3: Compra | I3: Estoque XP | J3: 18600 | K3: 18600 | L3: 206117.18 | M3: Finalizada | N3: 0.02 | O3: =N3*L3 -> 4122.3436
B4: RICARDO SOUZA DIAS | C4: 211007 | D4: 49894 | E4: Riza Malls Feeder FII RL | F4: 46064 | G4: 11:32:11 | H4: Compra | I4: Estoque XP | J4: 249 | K4: 249 | L4: 25473.53 | M4: Finalizada | N4: 0.02 | O4: =N4*L4 -> 509.4706
B5: BRUNO BARKI GAMEZ | C5: 293951 | D5: 25619 | E5: JHSF Capital Malls Feeder FII RL | F5: 46071 | G5: 14:02:30 | H5: Compra | I5: Estoque XP | J5: 4600 | K5: 4600 | L5: 51595.59 | M5: Finalizada | N5: 0.02 | O5: =N5*L5 -> 1031.9118
B6: RAFAEL MARINO CORREA DE SA MAQUIEIRA | C6: 324364 | D6: 25619 | E6: JHSF Capital Malls Feeder FII RL | F6: 46065 | G6: 11:00:59 | H6: Compra | I6: Estoque XP | J6: 1000 | K6: 1000 | L6: 11216.02 | M6: Finalizada | N6: 0.02 | O6: =N6*L6 -> 224.3204
B7: ANALU FERREIRA DE ALMEIDA | C7: 362329 | D7: 49894 | E7: Riza Malls Feeder FII RL | F7: 46058 | G7: 16:04:20 | H7: Compra | I7: Estoque XP | J7: 300 | K7: 300 | L7: 30656.97 | M7: Finalizada | N7: 0.02 | O7: =N7*L7 -> 613.1394
B8: ANALU FERREIRA DE ALMEIDA | C8: 362329 | D8: 49894 | E8: Maua Lajes Corporativas Feeder FII RL - Senior | F8: 46058 | G8: 16:04:46 | H8: Compra | I8: Estoque XP | J8: 200 | K8: 200 | L8: 20912.42 | M8: Finalizada | N8: 0.02 | O8: =N8*L8 -> 418.2484
B9: ANALU FERREIRA DE ALMEIDA | C9: 362329 | D9: 49894 | E9: AZQA11 - AZ Quest Luna - FIAgro | F9: 46075 | G9: 16:54:08 | H9: Compra | I9: Estoque XP | J9: 1472 | K9: 1472 | L9: 14716.38 | M9: Finalizada | N9: 0.02 | O9: =N9*L9 -> 294.3276
B10: AVELINO PEREIRA DOS SANTOS JUNIOR | C10: 542586 | D10: 21468 | E10: IMOV11 - Navi Hedge Fund | F10: 46062 | G10: 15:31:47 | H10: Compra | I10: Estoque XP | J10: 3200 | K10: 3200 | L10: 30477.22 | M10: Finalizada | N10: 0.02 | O10: =N10*L10 -> 609.5444
B11: AVELINO PEREIRA DOS SANTOS JUNIOR | C11: 542586 | D11: 21468 | E11: VGPR11 - Valora Imobiliário Multiestratégia Premium | F11: 46062 | G11: 15:34:39 | H11: Compra | I11: Estoque XP | J11: 2400 | K11: 2400 | L11: 22672.54 | M11: Finalizada | N11: 0.02 | O11: =N11*L11 -> 453.4508
B12: AVELINO PEREIRA DOS SANTOS JUNIOR | C12: 542586 | D12: 21468 | E12: AZPR11 - AZ Quest Panorama Crédito Imob. | F12: 46062 | G12: 15:46:47 | H12: Compra | I12: Estoque XP | J12: 813 | K12: 813 | L12: 7887.91 | M12: Finalizada | N12: 0.02 | O12: =N12*L12 -> 157.7582
B13: AVELINO PEREIRA DOS SANTOS JUNIOR | C13: 542586 | D13: 21468 | E13: JHSF Capital Malls Feeder FII RL | F13: 46063 | G13: 12:24:46 | H13: Compra | I13: Estoque XP | J13: 3000 | K13: 3000 | L13: 33646.23 | M13: Finalizada | N13: 0.02 | O13: =N13*L13 -> 672.9246
B14: AVELINO PEREIRA DOS SANTOS JUNIOR | C14: 542586 | D14: 21468 | E14: AZPR11 - AZ Quest Panorama Crédito Imob. | F14: 46077 | G14: 11:18:39 | H14: Compra | I14: Estoque XP | J14: 2090 | K14: 2090 | L14: 20340.76 | M14: Finalizada | N14: 0.02 | O14: =N14*L14 -> 406.8152
... B70: FRANCISCO GUILHIEN GOMES JUNIOR | C70: 18872460 | D70: 74304 | E70: JHSF Capital Malls Feeder FII RL | F70: 46076 | G70: 10:29:42 | H70: Compra | I70: Estoque XP | J70: 4510 | K70: 4510 | L70: 49977.88 | M70: Finalizada | N70: 0.02 | O70: =N70*L70 -> 999.5576

Sheet COE
B2: Código do ssessor | C2: Código do Cliente | D2: Tipo | E2: Ativo | F2: Data | G2: Hora | H2: Financeiro | I2: Situação | J2: Comissão % | K2: Receita
B3: 21468 | C3: 1579 | D3: Primaria | E3: XP Ouro - Bidirecional - 5y - 11.02.2026 | F3: 10/02/2026 | G3: 19:11:56 | H3: 3000 | I3: Liquidada | J3: 0.045 | K3: =H3*J3 -> 135
B4: 23648 | C4: 2716663 | D4: Primaria | E4: XP Ouro - Bidirecional - 5y - 20.02.2026 | F4: 19/02/2026 | G4: 13:58:35 | H4: 11900 | I4: Liquidada | J4: 0.045 | K4: =H4*J4 -> 535.5
B5: 23648 | C5: 4234049 | D5: Primaria | E5: XP Ouro - Bidirecional Limitado - 3y - 20.02.2026 | F5: 19/02/2026 | G5: 09:52:54 | H5: 20000 | I5: Liquidada | J5: 0.02 | K5: =H5*J5 -> 400
B6: 21468 | C6: 4925492 | D6: Primaria | E6: XP Ações Defesa Militar EUA - Alta Alavancada - 5y - 25.02.2026 | F6: 06/02/2026 | G6: 12:37:04 | H6: 5000 | I6: Solicitada | J6: 0.04 | K6: =H6*J6 -> 200
